django_talos-0.20.1215.dist-info/DESCRIPTION.rst
django_talos-0.20.1215.dist-info/METADATA
django_talos-0.20.1215.dist-info/RECORD
django_talos-0.20.1215.dist-info/WHEEL
django_talos-0.20.1215.dist-info/metadata.json
django_talos-0.20.1215.dist-info/top_level.txt
talos/__init__.py
talos/admin.py
talos/apps.py
talos/forms.py
talos/middleware.py
talos/models.py
talos/urls.py
talos/views.py
talos/compatibility/__init__.py
talos/compatibility/auth.py
talos/directory/__init__.py
talos/directory/basic_credential.py
talos/directory/basic_identity.py
talos/directory/onetimepassword.py
talos/directory/subnet.py
talos/directory/token_credential.py
talos/helpers/__init__.py
talos/helpers/admin.py
talos/helpers/discovery.py
talos/helpers/migration.py
talos/helpers/models.py
talos/helpers/session.py
talos/management/__init__.py
talos/management/abstract_command.py
talos/management/commands/__init__.py
talos/management/commands/change_role_permission.py
talos/management/commands/change_role_priviledge.py
talos/management/commands/create_basic_credential.py
talos/management/commands/create_basic_identity.py
talos/management/commands/create_principal.py
talos/management/commands/create_role.py
talos/management/commands/create_role_membership.py
talos/management/commands/update_basic_credential.py
talos/management/commands/update_principal.py
talos/management/commands/update_role.py
talos/migrations/0001_initial.py
talos/migrations/__init__.py
talos/static/talos/admin.css
talos/templates/talos/_base.html
talos/templates/talos/index.html
talos/templates/talos/basic_login/index.html
talos/templates/talos/basic_password_change/confirm_done.html
talos/templates/talos/basic_password_change/confirm_edit.html
talos/templates/talos/basic_password_reset/confirm_done.html
talos/templates/talos/basic_password_reset/confirm_edit.html
talos/templates/talos/basic_password_reset/request_done.html
talos/templates/talos/basic_password_reset/request_edit.html
talos/templates/talos/basic_password_reset/request_email_body.html
talos/templates/talos/basic_password_reset/request_email_body.txt
talos/templates/talos/basic_password_reset/request_email_subject.txt
